README.rst
setup.py
querystring/__init__.py
querystring/querystring.py
querystring.egg-info/PKG-INFO
querystring.egg-info/SOURCES.txt
querystring.egg-info/dependency_links.txt
querystring.egg-info/top_level.txt
tests/__init__.py
tests/querystring_test.py