Metadata-Version: 1.0
Name: querystring
Version: 0.1.0
Summary: Python port of the node.js querystring module
Home-page: UNKNOWN
Author: UNKNOWN
Author-email: UNKNOWN
License: UNKNOWN
Platform: UNKNOWN
